pyhole6/__init__.py
pyhole6/client.py
pyhole6/exceptions.py
pyhole6/logger.py
pyhole6/models.py
pyhole6/resources/__init__.py
pyhole6/resources/base.py
pyhole6/resources/dns.py
pyhole6/resources/history.py
pyhole6/resources/stats.py
pyhole6-0.0.4.dist-info/LICENSE
pyhole6-0.0.4.dist-info/METADATA
pyhole6-0.0.4.dist-info/WHEEL
pyhole6-0.0.4.dist-info/RECORD
