Metadata-Version: 2.1
Name: pyhole6
Version: 0.0.4
Summary: A REST API client for pihole v6
License: GPLv3
Author: Mike Introini
Requires-Python: >=3.9,<4.0
Classifier: License :: Other/Proprietary License
Classifier: Programming Language :: Python :: 3
Classifier: Programming Language :: Python :: 3.9
Classifier: Programming Language :: Python :: 3.10
Classifier: Programming Language :: Python :: 3.11
Classifier: Programming Language :: Python :: 3.12
Classifier: Programming Language :: Python :: 3.13
Requires-Dist: aiohttp (>=3.11.12,<4.0.0)
Requires-Dist: pytest (>=8.3.4,<9.0.0)
Requires-Dist: pytest-aiohttp (>=1.1.0,<2.0.0)
Requires-Dist: pytest-asyncio (>=0.25.3,<0.26.0)
